Metadata-Version: 1.0
Name: django-ranged-fileresponse
Version: 0.1.1
Summary: Modified Django FileResponse that adds Content-Range headers.
Home-page: https://github.com/wearespindle/django-ranged-fileresponse
Author: Spindle
Author-email: jeroen@wearespindle.com
License: MIT
Platform: UNKNOWN
